{
    "": "Unknown",
    "#atleticonacional.": "Colombia",
    "#healthcrusader": "Unknown",
    "#name?": "United States",
    "#newcastle  england": "United Kingdom",
    "#socal for life!": "United States",
    "$outh central la": "United States",
    "(65/65) fab queens": "United States",
    "-swimming in glass of wine_-": "United States",
    ". ruhrstadt .|. murstadt .": "Austria",
    "..., tn": "United States",
    "0/4 0/4 james/6 [pb]": "United Kingdom",
    "08.09.14.  04.14.15.": "Unknown",
    "1/5+maddie": "United States",
    "1/6 1/5 1/2": "Unknown",
    "10.1.14.": "United States",
    "10/12/15": "United States",
    "11/13/15": "Netherlands",
    "12 church st, boston, ma 02116": "United States",
    "1219, ca": "United States",
    "127.0.0.1": "Unknown",
    "12th october 2015 - 1d concert": "Unknown",
    "1393 pembina hwy, winnipeg, mb": "Canada",
    "14th grader @ wsu": "Unknown",
    "19 scotland": "United Kingdom",
    "1d  5h  jb": "United States",
    "2-jan": "United States",
    "20": "United States",
    "200413 || 280614": "Unknown",
    "215": "United States",
    "22 floh": "United States",
    "225/504/985": "Turkey",
    "252~757": "South Korea",
    "26/02/15": "Japan",
    "264 roaming": "United States",
    "27.943168, -82.451712": "United States",
    "284  5": "United States",
    "3/4 + band": "Argentina",
    "3033 excelsior blvd #100, mpls": "United States",
    "304/704": "South Korea",
    "30; 25' 58s 45; 28' 60e": "United States",
    "323 main ave, fargo, nd 58102": "United States",
    "35.728851,140.017265": "Japan",
    "38.655626,-90.224502": "United States",
    "401": "United States",
    "408": "United States",
    "413": "United States",
    "43.122580,-87.914122": "United States",
    "455 abbott": "United States",
    "47 kent street gornal. dy3 1uu": "United Kingdom",
    "48 states": "United States",
    "5 e. figueroa st. santa barbata, ca 93101": "United States",
    "555-filk": "Germany",
    "6-feb": "United States",
    "6.659713,3.358762": "Nigeria",
    "610": "United States",
    "666 block city": "United States",
    "7.10.15": "United States",
    "703-757": "Turkey",
    "704 | coastal carolina": "United States",
    "716": "United States",
    "757": "United States",
    "805  619  562": "Turkey",
    "8150 santa fe dr, overland pa": "United States",
    "9 lightyears away": "United States",
    "904": "United States",
    "918": "United States",
    "931 / 912": "South Korea",
    "@home": "United States",
    "[band/4]": "United States",
    "_": "Unknown",
    "_ _": "Unknown",
    "_ __ ____": "United States",
    "_5209f38a": "Unknown",
    "_z_": "Netherlands",
    "a galaxy far, far away": "India",
    "a gutter in new jersey": "United States",
    "a gym": "United States",
    "a higher place": "United States",
    "a place": "India",
    "a van, down by the river": "United States",
    "a village near exeter": "United States",
    "aaarrgh": "Unknown",
    "aachen": "Germany",
    "aalborg": "Denmark",
    "aapka dil......": "India",
    "abbostsford, bc": "Canada",
    "aberdare, south wales": "United Kingdom",
    "aberdare, wales": "United Kingdom",
    "aberdeen": "United Kingdom",
    "aberdeen fl370": "Unknown",
    "aberdeenshire": "United Kingdom",
    "abruzzo, italy": "Italy",
    "abu dhabi, uae": "United Arab Emirates",
    "accra.": "Ghana",
    "acink tattoo studio": "United States",
    "aco": "United States",
    "adelaide, australia": "Australia",
    "africa": "South Africa",
    "ahead of the curve...(near dc)": "United States",
    "akl": "New Zealand",
    "akumal, mexico": "Mexico",
    "al": "United States",
    "al-madinah": "Saudi Arabia",
    "alabama, usa": "United States",
    "alamosa, co": "United States",
    "albany,new york.corporation st": "United States",
    "albany/long island": "United States",
    "alberta, canada": "Canada",
    "albuquerque, nm": "United States",
    "algeciras, andaluc_a": "Spain",
    "algonac & mt. pleasant, mi": "Unknown",
    "all over usa": "United States",
    "almadinah almunawarah": "Saudi Arabia",
    "almeria spain": "Spain",
    "alps": "France",
    "alternate universe": "United States",
    "altrincham": "United Kingdom",
    "america": "United States",
    "america credit": "United States",
    "america's dairyland": "United States",
    "ames, ia": "United States",
    "amsterdam": "Netherlands",
    "anderson, sc": "United States",
    "andover, hampshire": "United Kingdom",
    "angus, scotland": "United Kingdom",
    "ankh-morpok": "United Kingdom",
    "ann arbor, mi": "United States",
    "annapolis, md": "United States",
    "anywhere": "United States",
    "araatuba-sp": "Brazil",
    "aret": "Czechia",
    "argentina": "Argentina",
    "argyle, tx": "United States",
    "arizona": "United States",
    "arizona, usa": "United States",
    "arkansas": "United States",
    "arkham asylum": "United States",
    "arlington, texas": "United States",
    "arlington, va": "United States",
    "arlington//lubbock": "United States",
    "as above so below": "United States",
    "asexual paradise": "Unknown",
    "asheville, nc": "United States",
    "ashland, ohio": "United States",
    "askdemigod": "Unknown",
    "at a bar watching tv": "Unknown",
    "at the jaffa caf": "United States",
    "athens": "Greece",
    "athens, greece": "Greece",
    "athens, oh": "United States",
    "atherstone": "United Kingdom",
    "atl": "United States",
    "atl // athens": "United States",
    "atlanta": "United States",
    "atlanta  savannah": "United States",
    "atlanta clairmont": "United States",
    "atlanta, ga": "United States",
    "atlanta, georgia": "United States",
    "atlantis": "Bahamas",
    "atm": "United States",
    "auckland, nz": "New Zealand",
    "aurora": "United States",
    "austin": "United States",
    "austin tx": "United States",
    "austin, tx": "United States",
    "austin, tx and nashville,tn": "United States",
    "austin, tx, usa": "United States",
    "austintown, oh": "United States",
    "australia": "Australia",
    "avellaneda centro": "Argentina",
    "az": "United States",
    "azusa": "United States",
    "bacoor, calabarzon": "Philippines",
    "badlands": "United States",
    "baker city oregon": "United States",
    "bakersfield, ca": "United States",
    "baltimore, md": "United States",
    "baltimore.": "United States",
    "bandung": "Indonesia",
    "bangalore": "India",
    "bangalore, india": "India",
    "bangkok, thailand": "Thailand",
    "barcelona": "Spain",
    "barcelona pakistan": "Spain",
    "barcelona, catalua": "Spain",
    "barry, vale of glamorgan, uk": "United Kingdom",
    "bartlesville, ok": "United States",
    "barwick, ga": "United States",
    "basingstoke": "United Kingdom",
    "batavia, ohio": "United States",
    "battle creek, mi": "United States",
    "battlefield, missouri": "United States",
    "baudette, mn": "United States",
    "bavaria, germany": "Germany",
    "bay area": "United States",
    "bay area x boulder": "United States",
    "bay area, california, usa": "United States",
    "bay city, mi": "United States",
    "beacon, baby": "United States",
    "beautiful british columbia": "Canada",
    "beautiful orange county, ny": "United States",
    "beaverton, or": "United States",
    "beaverton, oregon": "United States",
    "bed": "United States",
    "bedford, uk": "United Kingdom",
    "bedworth": "United Kingdom",
    "bees?": "United States",
    "behind you": "Germany",
    "behind you.": "Germany",
    "beirut": "Lebanon",
    "belfast": "United Kingdom",
    "belfast, northern ireland": "United Kingdom",
    "belgique": "Belgium",
    "belgium": "Belgium",
    "belgravia": "United Kingdom",
    "belleville": "United States",
    "bellevue, wa": "United States",
    "bellingham, wa": "United States",
    "belmar, nj": "United States",
    "belmont, ca": "United States",
    "beloit, wi": "United States",
    "below the surface": "United Kingdom",
    "benicia, ca": "United States",
    "bergen, norway": "Norway",
    "berkeley,  ca": "United States",
    "berlin": "Germany",
    "berlin u girl 06/27/14": "Germany",
    "best file & email encryption": "Unknown",
    "bhopal, m.p. [india]": "India",
    "biarritz": "France",
    "bikini bottom": "United States",
    "birmingham": "United Kingdom",
    "birmingham uk": "United Kingdom",
    "birmingham, al": "United States",
    "birmingham, uk": "United Kingdom",
    "birmingham/nottingham": "United Kingdom",
    "bismarck-mandan, nd": "United States",
    "blackcity": "United States",
    "blandford forum, england": "United Kingdom",
    "blue neighbourhood": "United States",
    "blue springs, mo": "United States",
    "boca raton, fl": "United States",
    "bogot": "Colombia",
    "bogot, colombia": "Colombia",
    "boise idaho": "United States",
    "boise, id": "United States",
    "bolivia": "Bolivia",
    "bonn, germany": "Germany",
    "boone, nc": "United States",
    "boston": "United States",
    "boston / new york": "United States",
    "boston college": "United States",
    "boston, ma": "United States",
    "boston, ma.": "United States",
    "botwood, newfoundland": "Canada",
    "bournemouth": "United Kingdom",
    "bournemouth uk": "United Kingdom",
    "bournemouth, england": "United Kingdom",
    "bowden & birmingham, uk": "United Kingdom",
    "bracknell.": "United Kingdom",
    "braintree, essex, cm7 3nr": "United Kingdom",
    "branson, mo": "United States",
    "brantford/brant": "Canada",
    "bras_lia": "Brazil",
    "brasil": "Brazil",
    "brattleboro, vt": "United States",
    "brazil": "Brazil",
    "brighton": "United States",
    "brighton, england": "United Kingdom",
    "brighton, uk": "United Kingdom",
    "bristol": "United Kingdom",
    "bristol, england": "United Kingdom",
    "brittany's mouth or panties": "Unknown",
    "bronkhorstspruit/witbank": "South Africa",
    "bronx, ny": "United States",
    "brooklyn": "United States",
    "brooklyn ,yonkers ,": "United States",
    "brooklyn union": "United States",
    "brooklyn, new york": "United States",
    "brooklyn, new york shitty": "United States",
    "brooklyn, ny": "United States",
    "brooklyn/vincy": "United States",
    "broward, florida": "United States",
    "brownwood, tx": "United States",
    "brunaela me sigue _": "Unknown",
    "brussels belgium": "Belgium",
    "budapest - magyarorszg": "Hungary",
    "buena vista, co 81211": "United States",
    "buffalo new york": "United States",
    "buffalo ny": "United States",
    "buffalo, ny 716|135": "United States",
    "buffalo, ny.": "United States",
    "buffalo,ny": "United States",
    "burnaby, british columbia": "Canada",
    "burton upon trent, england": "United Kingdom",
    "by your side": "United States",
    "byron bay, nsw": "Australia",
    "c a l i f o r n i a": "United States",
    "ca.": "United States",
    "caduceus usa": "United States",
    "cairo, egypt": "Egypt",
    "calfornia": "United States",
    "calgary": "Canada",
    "calgary, alberta canada": "Canada",
    "cali": "Colombia",
    "cali. 5th street": "United States",
    "california": "United States",
    "california (coachella valley)": "United States",
    "california, usa": "United States",
    "california. the south part.": "United States",
    "caliii": "Canada",
    "cambridge": "United Kingdom",
    "cambridge uk": "United Kingdom",
    "cambridge, ma": "United States",
    "campinas - sp": "Brazil",
    "campo grande, ms, brasil": "Brazil",
    "can't decide": "Unknown",
    "canada": "Canada",
    "canada, montreal": "Canada",
    "canada.": "Canada",
    "canada/costa rica": "Costa Rica",
    "canandaigua ny": "United States",
    "candied island": "United States",
    "canisius college": "United States",
    "canterbury": "United Kingdom",
    "canton, oh": "United States",
    "cap.fed.bs.as.argentina": "Argentina",
    "cape town": "South Africa",
    "cape town, south africa": "South Africa",
    "caracas-venezuela": "Venezuela",
    "caracas/santiago": "Venezuela",
    "cardiff by the sea, ca": "United States",
    "carluke, lanarkshire, scotland": "United Kingdom",
    "carson, ca": "United States",
    "carthage, tx": "United States",
    "cary, nc": "United States",
    "casa erotica": "Belgium",
    "casal di principe": "Italy",
    "castle": "United States",
    "castleblayney co. monaghan": "Ireland",
    "cayman island": "Cayman Islands",
    "cedar hills, ut": "United States",
    "celestial hemisphere": "United States",
    "central kansas": "United States",
    "central texas": "United States",
    "central valley": "United States",
    "ch 8840 switzerland": "Switzerland",
    "champaign, il": "United States",
    "champions gate, fl": "United States",
    "chapel hill, nc": "United States",
    "charleston, sc": "United States",
    "charleston, sc, united states": "United States",
    "charlotte": "United States",
    "charlotte, nc": "United States",
    "charlottesville, va": "United States",
    "chattanooga tn": "United States",
    "check the lists!": "Brazil",
    "chennai": "India",
    "chepstow, monmouthshire": "United Kingdom",
    "cheshire": "United Kingdom",
    "chester": "United States",
    "chester, uk": "United Kingdom",
    "chester, united kingdom": "United Kingdom",
    "chesterfield, england": "United Kingdom",
    "chicago": "United States",
    "chicago, il": "United States",
    "chicago/chirilla, south side": "Unknown",
    "chicago/los angeles": "United States",
    "chicagoland and north carolina": "United States",
    "chicagoland--western suburbs": "United States",
    "chile": "Chile",
    "chillax'n in the deepsouth": "India",
    "chilling": "Canada",
    "chipotle": "United States",
    "chorley": "United Kingdom",
    "christian's arms": "United States",
    "chs": "United States",
    "cincinnati": "United States",
    "cincinnati, ohio": "United States",
    "city of angels": "United States",
    "city of evil": "United States",
    "city of london, london": "United Kingdom",
    "clark atlanta university": "United States",
    "clcncl": "India",
    "cle/bg": "United States",
    "cleveland": "United States",
    "cleveland oh": "United States",
    "cleveland state": "United States",
    "cleveland, oh": "United States",
    "cleveland, ohio": "United States",
    "clio. mi": "United States",
    "clontarf, dublin 3, ireland.": "Ireland",
    "cloud9": "United States",
    "club tropicana": "United States",
    "co": "United States",
    "code room": "United States",
    "colchester": "United Kingdom",
    "colchester, essex, uk": "United Kingdom",
    "college park/flagstone": "United States",
    "college station": "United States",
    "cologne, north rhine-westphalia": "Germany",
    "colombia": "Colombia",
    "colombo, sri lanka": "Sri Lanka",
    "colorado": "United States",
    "colorado springs, co": "United States",
    "colorado, usa": "United States",
    "columbia": "United States",
    "columbia mo": "United States",
    "columbia, missouri": "United States",
    "columbia, mo": "United States",
    "columbia, sc": "United States",
    "columbus via the 330": "United States",
    "columbus, ms": "United States",
    "columbus, ne": "United States",
    "columbus, oh": "United States",
    "columbus, ohio": "United States",
    "community chest": "United States",
    "compton": "United States",
    "concord, ca": "United States",
    "constanta, romania": "Romania",
    "contagem, mg, brazil": "Brazil",
    "cookridge, leeds, england": "United Kingdom",
    "coppinstate19": "Unknown",
    "coquitlam, bc, canada": "Canada",
    "coral gables, florida 33134": "United States",
    "coralville, ia": "United States",
    "corner of 4th & fremont street": "United States",
    "cornwall": "United Kingdom",
    "corpus christi": "United States",
    "county durham": "United Kingdom",
    "county of simcoe": "Canada",
    "covington, kentucky": "United States",
    "cranfield, uk": "United Kingdom",
    "crewe, cheshire!/manchester": "United Kingdom",
    "crook county, il": "United States",
    "ct": "United States",
    "cupertino, ca": "United States",
    "curitiba, paran": "Brazil",
    "da city!!": "United States",
    "da grove": "United States",
    "da nando's with @niallofficial": "Unknown",
    "dallas": "United States",
    "dallas, texas hold em": "United States",
    "dallas, tx": "United States",
    "dallas,tx  worldwide": "United States",
    "daly city, ca": "United States",
    "damaged": "United States",
    "damascus, maryland": "United States",
    "davelackie.com": "Unknown",
    "daventry": "United Kingdom",
    "day6 promoter": "Unknown",
    "dayton, oh": "United States",
    "dazhane's": "Unknown",
    "dc": "United States",
    "deadend, uk": "United Kingdom",
    "death city": "United States",
    "death city.": "United States",
    "decatur, al": "United States",
    "deceased.": "United States",
    "deer park, ny": "United States",
    "defcom 3": "India",
    "dekalb, il": "United States",
    "delaware": "United States",
    "delaware, usa": "United States",
    "delray beach, laguna beach": "United States",
    "demacia": "China",
    "denmark": "Denmark",
    "denton": "United States",
    "denver, co": "United States",
    "denver, colorado": "United States",
    "derbyshire": "United Kingdom",
    "des moines, iowa": "United States",
    "detroit playa": "United States",
    "detroit, chicago, st. louis": "United States",
    "detroit, mi": "United States",
    "deutschland": "Germany",
    "devon": "United Kingdom",
    "devon, uk": "United Kingdom",
    "devonport, plymouth": "United Kingdom",
    "df": "Brazil",
    "dfw   houston": "United States",
    "diaspora": "United States",
    "didcot oxfordshire": "United Kingdom",
    "dimapur, nagaland": "India",
    "dinah/6": "United States",
    "district 12  cabin 13": "United States",
    "district 13": "United States",
    "dm[v]": "Dominica",
    "dmv": "United States",
    "dominican republic": "Dominican Republic",
    "dorchester, ma": "United States",
    "dorset": "United Kingdom",
    "dothan, al": "United States",
    "dover, nh": "United States",
    "down and dirty in the dmv": "Unknown",
    "downriver, mi": "United States",
    "dressa&ceci": "Unknown",
    "dricki's dream child": "Unknown",
    "dtw  grr": "United States",
    "dtximports": "United States",
    "dubai": "United Arab Emirates",
    "dubai, uae": "United Arab Emirates",
    "dubai, united arab emirates": "United Arab Emirates",
    "dublin": "Ireland",
    "dublin - ireland": "Ireland",
    "dublin city, ireland": "Ireland",
    "dublin via west (west) cork": "Ireland",
    "dublin, ireland": "Ireland",
    "dublin, irlande": "Ireland",
    "dublin/london": "United Kingdom",
    "dunder mifflin": "Canada",
    "dunfermline": "United Kingdom",
    "dunfermline, scotland": "United Kingdom",
    "durban": "South Africa",
    "durban, south africa": "South Africa",
    "durbz": "United Kingdom",
    "durham / liverpool": "United Kingdom",
    "durham, england": "United Kingdom",
    "earth": "United States",
    "east atlanta, ga": "United States",
    "east chicago, in": "United States",
    "east end, pittsburgh, pa": "United States",
    "east harlem, nyc.": "United States",
    "east lansing, mi": "United States",
    "east london": "South Africa",
    "east of the uk": "United Kingdom",
    "east yorkshire": "United Kingdom",
    "eastcarolinauniv.": "United States",
    "ecuador": "Ecuador",
    "edina, mn": "United States",
    "edinburgh": "United Kingdom",
    "edinburgh scotland": "United Kingdom",
    "edmond, ok": "United States",
    "edmonton, ab": "Canada",
    "edmonton, alberta": "Canada",
    "edmonton, alberta, canada": "Canada",
    "edwardsville, illinois": "United States",
    "egypt": "Egypt",
    "el cajon, ca": "United States",
    "el centro": "United States",
    "ely": "United States",
    "emmaus pa": "United States",
    "enchanted forest": "United States",
    "england": "United Kingdom",
    "england, united kingdom": "United Kingdom",
    "enugu , nigeria": "Nigeria",
    "espaa": "Portugal",
    "essex, uk": "United Kingdom",
    "estrat_sfera.": "Brazil",
    "etsu '19": "Japan",
    "europe": "Unknown",
    "evanston, il usa": "United States",
    "evansville, indiana": "United States",
    "everywhere": "United States",
    "evillage": "Netherlands",
    "ex model & blogger": "Unknown",
    "exeter, england": "United Kingdom",
    "fairfield county,ct": "United States",
    "fairfield, ca": "United States",
    "fangirling world": "Unknown",
    "fareham": "United Kingdom",
    "farmer land": "United States",
    "fct, abuja": "Nigeria",
    "fema region vi": "United States",
    "ferguson mo": "United States",
    "fife, scotland": "United Kingdom",
    "finland": "Finland",
    "fl": "United States",
    "florida": "United States",
    "florida & colorado": "United States",
    "florida, usa": "United States",
    "focused on my future": "Unknown",
    "forres, scotland": "United Kingdom",
    "fort collins, co": "United States",
    "fort lauderdale, fl": "United States",
    "fort smith, ar": "United States",
    "fort worth, texas": "United States",
    "forte da casa": "Portugal",
    "fortress radio": "United States",
    "foxboro, ma 02035": "United States",
    "foxborough, ma gillettestadium": "United States",
    "france": "France",
    "france  blandine": "France",
    "francistown,botswana": "Botswana",
    "freakinhategale45": "Unknown",
    "fredericton, nb": "Canada",
    "free periscope training !": "Unknown",
    "freemartinis.deviantart.com": "Unknown",
    "frequent traveler": "United States",
    "frndenberg": "Norway",
    "from brooklyn.wat it look like": "Unknown",
    "from the bay to (dt)la": "Unknown",
    "from the black country": "United Kingdom",
    "front range, colorado": "United States",
    "frostburg md": "United States",
    "ftnytyl": "Unknown",
    "g:3 s:14 b:67": "United States",
    "ga": "United States",
    "gaborone , botswana": "Botswana",
    "gaborone, botswana": "Botswana",
    "gaia": "United States",
    "gainesville, fl": "United States",
    "gainesville, florida usa": "United States",
    "gainesville, georgia": "United States",
    "gainesville, oklahoma": "United States",
    "gambrills": "United States",
    "garden state": "United States",
    "gbg": "Sweden",
    "georgia": "United States",
    "georgia, usa": "United States",
    "germany": "Germany",
    "germany, aachen": "Germany",
    "get 2 free ebooks today!!!": "Unknown",
    "get me a normani video": "Unknown",
    "getting money": "United States",
    "ggl_di4 f_s": "United States",
    "ghana": "Ghana",
    "glasgow": "United Kingdom",
    "glasgow, scotland": "United Kingdom",
    "global": "United States",
    "global perspective": "United States",
    "glomaha": "Unknown",
    "gloucester/birmingham": "United Kingdom",
    "god's country": "United States",
    "god's world-cali-sacramento": "United States",
    "gotham": "United States",
    "gothenburg, sweden": "Sweden",
    "government agencies": "United States",
    "granby, ct": "United States",
    "grand bay, al": "United States",
    "grand rapids, mi": "United States",
    "great britain": "United Kingdom",
    "greater nyc area": "United States",
    "greater slc, utah, usa, earth": "Unknown",
    "greater toronto area": "Canada",
    "greater washington dc": "United States",
    "greece": "Greece",
    "greece crete": "Greece",
    "green bay, wi": "United States",
    "greenfield & waukesha wi": "United States",
    "greenhous meadow, sy2 6st": "United Kingdom",
    "greenland": "Greenland",
    "greensboro": "United States",
    "greensboro, nc": "United States",
    "greensboro, north carolina": "United States",
    "greenville s.c": "United States",
    "greenville, sc": "United States",
    "greenwich & la": "United States",
    "gretton, england": "United Kingdom",
    "grimsby, england": "United Kingdom",
    "guadalajara, jalisco; mexico": "Mexico",
    "gunztown": "United States",
    "h town": "United States",
    "h-town/ mo city": "United States",
    "h/4 soon": "Japan",
    "hackney": "United Kingdom",
    "hackney, london, uk": "United Kingdom",
    "halfway, sheffield": "United Kingdom",
    "halifax": "United States",
    "halifax nova scotia": "Canada",
    "halifax, nova scotia": "Canada",
    "halifax, nova scotia, canada": "Canada",
    "halloweentown": "United States",
    "haltom city, tx": "United States",
    "hamburg, germany": "Germany",
    "hamilton, on": "Canada",
    "hamilton,canada": "Canada",
    "hampshire": "United Kingdom",
    "hampshire, uk": "United Kingdom",
    "hampton roads virginia": "United States",
    "hampton, va": "United States",
    "hamtramck, michigan": "United States",
    "harare": "Zimbabwe",
    "harbor springs, mi": "United States",
    "harlem, ny": "United States",
    "harrogate": "United Kingdom",
    "hartlepool": "United Kingdom",
    "hastings, uk": "United Kingdom",
    "haven": "United States",
    "hazlet, nj": "United States",
    "heart lost to australia & ire": "Unknown",
    "heaven": "United States",
    "hell (aka florida)": "Unknown",
    "hell (venezuela)": "Unknown",
    "hell a": "United States",
    "hell town, uk": "United Kingdom",
    "helsinki": "Finland",
    "here": "United States",
    "here & there": "United States",
    "here now": "United States",
    "here!": "United States",
    "here, there and everywhere": "United States",
    "here, there, everywhere!": "United States",
    "here_there": "United States",
    "herndon, va": "United States",
    "hertfordshire, uk": "United Kingdom",
    "hoboken nj": "United States",
    "hofstra university 18'": "United States",
    "hogsmeade": "United States",
    "hogwarts | brasil": "Brazil",
    "hollywood": "United States",
    "honeymoon ave.": "United States",
    "honeymoon ve.": "Hong Kong",
    "honolulu, hi": "United States",
    "hood college '19": "United States",
    "hoorn": "Netherlands",
    "hotels around the world": "United States",
    "houma, la usa": "United States",
    "houston": "United States",
    "houston tx": "United States",
    "houston | cyp": "United States",
    "houston, texas": "United States",
    "houston, tx": "United States",
    "houston,tx": "United States",
    "http://www.phoenixopera.org": "United States",
    "htx": "United States",
    "htx  kentucky": "United States",
    "huddersfield/newcastle": "United Kingdom",
    "hudson, wi": "United States",
    "hull": "United Kingdom",
    "hull, england": "United Kingdom",
    "huntsville   t-town": "United States",
    "huntsville, al": "United States",
    "huyton, liverpool": "United Kingdom",
    "hyrule": "United States",
    "i am here..": "Italy",
    "ibadan, nigeria": "Nigeria",
    "ichigao": "Japan",
    "icon? aogiri penta.": "Unknown",
    "ig: bailey_kayy": "India",
    "il": "United States",
    "illinois": "United States",
    "illinois state university": "United States",
    "illinois, usa": "United States",
    "in a galaxy far far away": "India",
    "in a world of my own": "United States",
    "in another castle": "United States",
    "in hell": "India",
    "in lala land, dreaming": "India",
    "in luis's heart _": "United States",
    "in my business.": "India",
    "in my own skin": "United States",
    "in pussy and on dick": "Unknown",
    "in the d!": "United States",
    "in the stars": "India",
    "in the world": "United States",
    "in your closet..(creepy smirk)": "Unknown",
    "in your wildest dreams ;)": "United States",
    "india": "India",
    "india-france": "France",
    "indiana": "United States",
    "indiana _": "United States",
    "indiana, usa": "United States",
    "indianapolis": "United States",
    "indianapolis, in": "United States",
    "indianapolis,in": "United States",
    "indonesia": "Indonesia",
    "indonesia, uk": "Indonesia",
    "infinitely yours seoul": "Unknown",
    "inglewood,ca": "United States",
    "instagram -iammicic": "Paraguay",
    "instagram @destructiblee": "Unknown",
    "international": "Canada",
    "interstellar": "United States",
    "iowa": "United States",
    "iowa, usa": "United States",
    "iphone: -15.252235,28.165728": "United States",
    "iphone: 40.826569,-73.931259": "United States",
    "iphone: 41.330138,-72.060871": "United States",
    "iphone: 44.051918,-91.653076": "Canada",
    "ireland": "Ireland",
    "ireland lad": "Ireland",
    "irvine, california": "United States",
    "is everything ___": "Canada",
    "isla nublar": "Costa Rica",
    "islamabad, pakistan": "Pakistan",
    "island of quivering nrvs": "Unknown",
    "israel": "Israel",
    "italy": "Italy",
    "italy, naples": "Italy",
    "j u s t i n s  h o u s e": "United States",
    "jabriya": "Kuwait",
    "jackson ms": "United States",
    "jacksonville beach, fl": "United States",
    "jacksonville, fl": "United States",
    "jakarta, indonesia": "Indonesia",
    "jamaica plain, ma": "United States",
    "japan": "Japan",
    "jdd_h": "United States",
    "jefferson city, missouri": "United States",
    "jerez / mesas de asta": "Spain",
    "jersey": "Jersey",
    "jersey city, nj": "United States",
    "jitters": "United States",
    "johannesburg": "South Africa",
    "johannesburg, south africa": "South Africa",
    "johannesburgcapetownnigeria": "Unknown",
    "johnson rd.": "United States",
    "johnstown, pa": "United States",
    "jonesboro, arkansas": "United States",
    "joplin, mo.": "United States",
    "jpiter": "United States",
    "judsonia, ar": "United States",
    "julos, midi-pyrnes": "France",
    "k-town": "United States",
    "kaduna": "Nigeria",
    "kakariko village": "New Zealand",
    "kalamazoo , mi": "United States",
    "kalamazoo mi.": "United States",
    "kalamazoo, mi": "United States",
    "kalu@blackedout.co.uk": "Unknown",
    "kampala, uganda": "Uganda",
    "kano": "Nigeria",
    "kanon town, ca": "Bangladesh",
    "kansas city": "United States",
    "kansas city  atl": "United States",
    "kansas city, mo": "United States",
    "kansas, usa": "United States",
    "kashmir": "India",
    "kaylee | 16 | she/her": "United States",
    "kc clique": "United States",
    "kearny, new jersey": "United States",
    "kent": "United States",
    "kentucky": "United States",
    "kenya": "Kenya",
    "khartoum / dubai": "Sudan",
    "kigali": "Rwanda",
    "kill devil hills, nc": "United States",
    "kilmarnock": "United Kingdom",
    "kingston, jamaica": "Jamaica",
    "kingways": "United States",
    "kisumu city": "Kenya",
    "kitchener, ontario": "Canada",
    "kluang | johor": "Malaysia",
    "knocknaheeny, cork": "Ireland",
    "knoxville, tennessee": "United States",
    "knoxville, tn": "United States",
    "kodi's world": "India",
    "kolkata": "India",
    "kortrijk, belgium": "Belgium",
    "kr": "South Korea",
    "kristen": "United States",
    "ksa": "Saudi Arabia",
    "kwuait": "Kuwait",
    "ky": "Cayman Islands",
    "kylee & madeline make me :))": "Unknown",
    "l'cosse libre/scotland": "Unknown",
    "la": "United States",
    "la capital, argentina": "Argentina",
    "la vista": "United States",
    "la, ga, nyc, mia, mn": "Unknown",
    "lafayette, indiana": "United States",
    "lagos": "Nigeria",
    "lagos and abuja": "Nigeria",
    "lagos kent": "Nigeria",
    "lagos nigeria": "Nigeria",
    "lagos, nigeria": "Nigeria",
    "lagos,nigeria": "Nigeria",
    "lagrange, ga.": "United States",
    "lajpat nagar new delhi": "India",
    "lake charles": "United States",
    "lake city, florida": "United States",
    "lake tahoe": "United States",
    "lakewood nj": "United States",
    "lakewood, ca": "United States",
    "lancashire": "United Kingdom",
    "lancaster, wi": "United States",
    "land of mary": "United States",
    "lansing, ks": "United States",
    "las cruces, nm": "United States",
    "las vegas": "United States",
    "las vegas / oc": "United States",
    "las vegas nv": "United States",
    "las vegas, nv": "United States",
    "launched 2015, national": "United States",
    "lawrence, ks": "United States",
    "laws & jealous, cauliflowernia": "Unknown",
    "lead zero": "United States",
    "left coast": "United States",
    "lehigh valley, pa": "United States",
    "leicester": "United Kingdom",
    "les pennes mirabeau, france": "France",
    "leyland, lancashire": "United Kingdom",
    "lgbt": "United States",
    "lhr": "United Kingdom",
    "library.": "United States",
    "lil afghanistan": "Canada",
    "limerick, ireland": "Ireland",
    "lincoln, ne": "United States",
    "lisboa, portugal": "Portugal",
    "little rock, arkansas": "United States",
    "liverpool": "United States",
    "liverpool england": "United Kingdom",
    "liverpool, england": "United Kingdom",
    "livingston county mi": "United States",
    "livonia, mi": "United States",
    "livorno": "Italy",
    "localglobal": "Germany",
    "location unfound": "Spain",
    "logan, ut": "United States",
    "logansport,in usa": "United States",
    "london": "United Kingdom",
    "london / mogadishu": "Somalia",
    "london and the cotswolds, uk": "United Kingdom",
    "london or n america": "United States",
    "london via california": "United States",
    "london, england": "United Kingdom",
    "london, ontario, canada": "Canada",
    "london, uk": "United Kingdom",
    "london, uk | chicago, il": "United Kingdom",
    "london, uk/new york, usa": "United States",
    "london, usa": "United States",
    "london.": "United Kingdom",
    "london//surrey etc.": "United Kingdom",
    "london/bergamo": "Italy",
    "london/washinton d.c.": "United States",
    "long beach": "United States",
    "long beach, ca": "United States",
    "long branch, nj": "United States",
    "long island": "United States",
    "long island city, ny": "United States",
    "lorton, va": "United States",
    "los angeles": "United States",
    "los angeles - new york": "United States",
    "los angeles, ca": "United States",
    "los angeles, ca, usa": "United States",
    "los angeles, california": "United States",
    "los angeles, sonoma, chicago": "Unknown",
    "los angeles.": "United States",
    "los banos, calabarzon": "Philippines",
    "los fresnos, tx": "United States",
    "los ngeles": "United States",
    "los santos": "Spain",
    "los santos, san andreas": "Spain",
    "losangeles": "United States",
    "losangeles, ca": "United States",
    "lost": "United States",
    "lost in utah.": "United States",
    "loudon, nh": "United States",
    "louisiana": "United States",
    "louisiana, mo": "United States",
    "louisiana, usa": "United States",
    "louisville, ky": "United States",
    "louisville, nebraska": "United States",
    "lowestoft": "United Kingdom",
    "luling, tx": "United States",
    "lund, sweden": "Sweden",
    "lusaka, zambia": "Zambia",
    "lyon": "France",
    "m!a:": "Germany",
    "m6. m42, m40, m25, a3": "Unknown",
    "made in #milwaukee": "United States",
    "madison, ms": "United States",
    "madison, wi / global": "United States",
    "madrid": "Spain",
    "madrid (spain)": "Spain",
    "madrid, espaa": "Spain",
    "mafikeng": "South Africa",
    "magnolia, arkansas": "United States",
    "main line": "United States",
    "main; @kan1shk3": "Unknown",
    "maine": "United States",
    "making money": "United States",
    "malang, jawa timur": "Indonesia",
    "malaysia": "Malaysia",
    "malden, ma": "United States",
    "maldives": "Maldives",
    "malibu, ca": "United States",
    "mama luigi": "United States",
    "manaus, amazonas": "Brazil",
    "manchester": "United Kingdom",
    "manchester & london, uk": "United Kingdom",
    "manchester ish via london": "United Kingdom",
    "manchester uk": "United Kingdom",
    "manchester, england": "United Kingdom",
    "manchester, uk": "United Kingdom",
    "manchester, uk.": "United Kingdom",
    "manhattan, ny": "United States",
    "manitoba, canada": "Canada",
    "maracaibo - edo zulia": "Venezuela",
    "marana, az": "United States",
    "marbella/manchester": "United States",
    "mars": "United States",
    "martin payne's crib in dc": "Unknown",
    "maryland": "United States",
    "mass and texas!": "United States",
    "massachusetts": "United States",
    "massachusetts, usa": "United States",
    "math city, tx": "United States",
    "mattawan, mi": "United States",
    "maui, hawaii": "United States",
    "mauritius": "Mauritius",
    "maven: severed": "Unknown",
    "mbabane swaziland": "Swaziland",
    "mcminnville, or": "United States",
    "medina": "Saudi Arabia",
    "melanie martinez": "United States",
    "melbourne": "Australia",
    "melbourne, australia": "Australia",
    "memphis, tn": "United States",
    "memphis, tn #bluffcity": "United States",
    "merseyside": "United Kingdom",
    "mesa arizona": "United States",
    "met ariana 9-11-15": "United States",
    "mexico": "Mexico",
    "mexico city": "Mexico",
    "mexico!": "Mexico",
    "mgctvdtocollinstfc": "Unknown",
    "mi.  fl. la": "United States",
    "miami": "United States",
    "miami beach, fl": "United States",
    "miami design district": "United States",
    "miami southridge sr. high": "United States",
    "miami, fl": "United States",
    "miami, florida": "United States",
    "michigan": "United States",
    "michigan, usa": "United States",
    "michoacan": "Mexico",
    "middle earth.": "United States",
    "midlands, great britain": "United Kingdom",
    "midwe$t . a.  costa rica": "Costa Rica",
    "milan italy": "Italy",
    "milan, italy": "Italy",
    "mile 327, +254": "United States",
    "milky way galaxy": "Canada",
    "milton keynes": "United Kingdom",
    "milwaukee": "United States",
    "milwaukee, wi": "United States",
    "minneapolis": "United States",
    "minneapolis, mn": "United States",
    "minneapolis-st. paul": "United States",
    "minnesota": "United States",
    "minnesota, usa": "United States",
    "missing, florida": "United States",
    "mississauga, on": "Canada",
    "mississauga, ontario": "Canada",
    "mississippi state, ms": "United States",
    "mobius": "United States",
    "mombasa, kenya": "Kenya",
    "mons - belgium": "Belgium",
    "montclair, nj": "United States",
    "monterey, ca": "United States",
    "monterrey, n.l.": "Mexico",
    "montreal": "Canada",
    "montreal, canada": "Canada",
    "montreal, quebec, canada": "Canada",
    "morelia, michoacn de ocampo": "Mexico",
    "morganville, nj": "United States",
    "morioh, japan": "Japan",
    "mornington, australia": "Australia",
    "mostly maine": "United States",
    "mother base": "United States",
    "mother earth": "United States",
    "moultrie, ga": "United States",
    "mount airy, nc": "United States",
    "mount olive, nc": "United States",
    "mountain view, ca": "United States",
    "moving": "United States",
    "msu": "United States",
    "mt": "United States",
    "mt.orab": "United States",
    "multiverse": "United Kingdom",
    "mumbai": "India",
    "mumbai, maharashtra": "India",
    "muncar, banyuwangi": "Indonesia",
    "munich, germany": "Germany",
    "murder city": "United States",
    "mv|rp": "United States",
    "mxico": "Mexico",
    "my family calls me smoosh": "Unknown",
    "my palace": "Portugal",
    "n. america | eu | aus | nz": "United States",
    "nadine mariam": "Germany",
    "nairobi": "Kenya",
    "nairobi, kenya": "Kenya",
    "nairobi,kenya": "Kenya",
    "nampa, id": "United States",
    "nan": "Unknown",
    "napoli, campania": "Italy",
    "nashville": "United States",
    "nashville, ga": "United States",
    "nashville, tn": "United States",
    "national capital region": "United States",
    "nationwide": "United States",
    "nazarick": "Unknown",
    "nbny | 25": "United States",
    "nc": "United States",
    "ne7": "United Kingdom",
    "nederland": "United States",
    "nederland, co": "United States",
    "nesbit, ms": "United States",
    "nest": "United States",
    "netherlands": "Netherlands",
    "nevada": "United States",
    "never you mind": "United States",
    "neverland": "United States",
    "new brighton, minnesota": "United States",
    "new delhi, delhi": "India",
    "new england": "United States",
    "new hampshire": "United States",
    "new haven, ct": "United States",
    "new jersey": "United States",
    "new jersey, usa": "United States",
    "new london, ct": "United States",
    "new mexico": "United States",
    "new orleans": "United States",
    "new orleans, la": "United States",
    "new providence, iowa": "United States",
    "new smyrna beach, fl": "United States",
    "new taipei city, taiwan": "Taiwan",
    "new york": "United States",
    "new york / los angeles": "United States",
    "new york and the world": "United States",
    "new york city": "United States",
    "new york gritty": "United States",
    "new york, new york": "United States",
    "new york, ny": "United States",
    "new york, united states": "United States",
    "new york, usa": "United States",
    "new york,ny": "United States",
    "new york/las vegas": "United States",
    "new york/london": "United States",
    "new yorker in san francisco": "United States",
    "new zealand": "New Zealand",
    "newark notts": "United Kingdom",
    "newark, nj": "United States",
    "newcastle // london": "United Kingdom",
    "newcastle upon tyne, england": "United Kingdom",
    "newcastle, england": "United Kingdom",
    "newcastle, uk": "United Kingdom",
    "newport beach, ca": "United States",
    "newport news, va": "United States",
    "newport, wales, uk": "United Kingdom",
    "newton, ma": "United States",
    "newyork": "United States",
    "nibiru": "Australia",
    "nicki's a$$": "United States",
    "nigeria": "Nigeria",
    "nigeria abuja": "Nigeria",
    "niles, oh": "United States",
    "nirvana": "United States",
    "nj": "United States",
    "no cho": "United States",
    "no dms [aurora, co]": "United States",
    "noida, allahabad, india": "India",
    "nomad": "United States",
    "norfolk. uk.": "United Kingdom",
    "norman, ok": "United States",
    "north africa": "North Africa",
    "north america & the world": "United States",
    "north carolina": "United States",
    "north carolina, usa": "United States",
    "north charleston, sc": "United States",
    "north east, england": "United Kingdom",
    "north haven, ct": "United States",
    "north huntingdon, pa": "United States",
    "north kanto": "Vietnam",
    "north korea": "North Korea",
    "north lundan": "United Kingdom",
    "north pole": "United States",
    "north side of that london": "United Kingdom",
    "north wales/liverpool": "United Kingdom",
    "north west, england": "United Kingdom",
    "north-east scotland": "United Kingdom",
    "north-east, uk.": "United Kingdom",
    "north-west": "South Africa",
    "northampton": "United Kingdom",
    "northampton town": "United States",
    "northern california": "United States",
    "northern hemisphere! pnw!": "Unknown",
    "northern ireland": "United Kingdom",
    "northern virginia": "United States",
    "northfield, ma": "United States",
    "northwest pa": "United States",
    "nostob, am": "United States",
    "nother.": "United States",
    "nottingham england uk": "United Kingdom",
    "nottingham, england.": "United Kingdom",
    "nottinghamshire": "United Kingdom",
    "nou camp.": "Spain",
    "nova scotia": "Canada",
    "nsk!": "United States",
    "ntx _ /// isaiah 40:31": "United States",
    "ny": "United States",
    "ny tri-state area": "United States",
    "ny/nj": "United States",
    "nyc": "United States",
    "nyc & the world": "United States",
    "nyc, usa": "United States",
    "nyc---dmv": "United States",
    "o.c. california": "United States",
    "oakfield, ny": "United States",
    "oakland": "United States",
    "oakland, ca": "United States",
    "oakland, ca, usa": "United States",
    "oakland, california usa": "United States",
    "oban, argyll, scotland, u.k.": "United Kingdom",
    "oceanside, ca": "United States",
    "odanah, wisconsin": "United States",
    "ogba, lagos": "Nigeria",
    "oh, usa (216)": "United States",
    "ohio": "United States",
    "ohio, usa": "United States",
    "okc": "United States",
    "oklahoma": "United States",
    "oklahoma city, ok": "United States",
    "oklahoma city, oklahoma, usa": "United States",
    "oklahoma state university.": "United States",
    "ollie | she/her | enfp": "United States",
    "olympia, wa": "United States",
    "olympic penisula wa.": "United States",
    "omaha": "United States",
    "omaha, ne": "United States",
    "on": "Canada",
    "on fire": "United States",
    "one-seven-one-eight": "United States",
    "oneohthreeohfour": "United States",
    "ontario": "Canada",
    "ontario ca": "United States",
    "ontario canada": "Canada",
    "ontario, canada": "Canada",
    "orange county": "United States",
    "orange county, ca": "United States",
    "oregon": "United States",
    "orlando, fl": "United States",
    "orlando, florida": "United States",
    "ormond via jax via ormond": "Unknown",
    "oromocto, nb": "Canada",
    "oshawa, ontario, canada": "Canada",
    "osu": "United States",
    "ottawa": "Canada",
    "ottawa, on": "Canada",
    "ottawa, ontario": "Canada",
    "ottawa, ontario, canada": "Canada",
    "our house": "United States",
    "out standing in a field": "United States",
    "outer space": "United States",
    "over that": "United States",
    "overland park, ks": "United States",
    "oxford": "United Kingdom",
    "oxford ohio": "United States",
    "ozarks": "United States",
    "pa, usa": "United States",
    "paarl": "South Africa",
    "paisley, scotland.": "United Kingdom",
    "pakistan": "Pakistan",
    "palestine & chicago": "United States",
    "palm beach, fl": "United States",
    "palmdale ca": "United States",
    "palmerston north, or foxton.": "New Zealand",
    "palmyra, va": "United States",
    "palo alto, ca": "United States",
    "panam": "Canada",
    "panama / greymane & drenden": "Unknown",
    "panama city fl": "United States",
    "panama city, florida": "United States",
    "paper chase": "United States",
    "paraaque  ph": "Philippines",
    "parabatai cubed _ #1 brook fan": "Unknown",
    "paradi$e": "United States",
    "paraguay": "Paraguay",
    "paris": "France",
    "paris - marseille": "France",
    "paris of the plains": "United States",
    "paris, ile-de-france": "France",
    "parry sound-muskoka ontario": "Canada",
    "parts unknown": "United States",
    "pawtucket ri, u.s army": "United States",
    "payno/4": "Mexico",
    "pdx": "United States",
    "pdx. and the internet.": "United States",
    "pe/pta/jhb  south africa": "Unknown",
    "penn.": "United States",
    "pennington, nj": "United States",
    "pennsylvania": "United States",
    "pennsylvania, usa": "United States",
    "pensacola fl": "United States",
    "perrine, florida": "United States",
    "peterborough": "United Kingdom",
    "peterborough, england": "United Kingdom",
    "philadelphia": "United States",
    "philadelphia & beyond": "United States",
    "philadelphia & pittsburgh": "United States",
    "philadelphia, pa": "United States",
    "philadelphia, pa.": "United States",
    "philippines": "Philippines",
    "philly/nyc": "United States",
    "phoenix": "United States",
    "phoenix, az": "United States",
    "pick north __": "United States",
    "pinamar": "Argentina",
    "pirates cove.": "United States",
    "piscataway, n.j.": "United States",
    "pittsburgh & miami": "United States",
    "pittsburgh, pa": "United States",
    "pizza planet": "United States",
    "places.": "Canada",
    "planet earth": "United States",
    "planet earth.": "United States",
    "plymouth, devon, uk": "United Kingdom",
    "plymouth, england": "United Kingdom",
    "plymouth, uk": "United Kingdom",
    "pocatello, id": "United States",
    "poland": "Poland",
    "pollenza. currently eindhoven.": "Unknown",
    "polluted beach": "India",
    "polokwane, south africa": "South Africa",
    "polska": "Poland",
    "pomeroy wa 99347": "United States",
    "pontypool, wales": "United Kingdom",
    "port glasgow, scotland": "United Kingdom",
    "port harcourt, nigeria": "Nigeria",
    "port-au-prince": "Haiti",
    "portland oregon": "United States",
    "portland, or": "United States",
    "portland, oregon": "United States",
    "portsmouth/chelmsford": "United Kingdom",
    "practicing kindness": "Unknown",
    "prague": "Czechia",
    "prague, czech republic": "Czechia",
    "prairie bible belt, sk. ca.": "Canada",
    "preston lancashire": "United Kingdom",
    "pretty world": "United States",
    "prichard, al": "United States",
    "princeton": "United States",
    "princeton, tx": "United States",
    "pronouns - dead/pool": "Unknown",
    "providence, ri": "United States",
    "psychedelia,disturbia": "Unknown",
    "queens ny": "United States",
    "queens, ny": "United States",
    "quincy, illinois": "United States",
    "quit creaping on me": "Unknown",
    "r_sselsheim, germany": "Germany",
    "radom, mazowieckie poland": "Poland",
    "ragin cajun": "United States",
    "raleigh nc": "United States",
    "raleigh, nc": "United States",
    "raleigh, north carolina, usa": "United States",
    "reading": "United States",
    "red roof city": "United States",
    "red velvet | sehun | 17 | etc": "United States",
    "reddit": "United States",
    "redmond, wa": "United States",
    "redmond, washington": "United States",
    "redwood city ca": "United States",
    "regina, sk": "Canada",
    "republic of korea": "South Korea",
    "rexford, ny": "United States",
    "rgf island": "Hong Kong",
    "richfield, mn": "United States",
    "richmond ca": "United States",
    "richmond, surrey, uk": "United Kingdom",
    "richmond, va": "United States",
    "richmond.": "United States",
    "ridge world": "United States",
    "ridgecrest ca lyles tn": "Unknown",
    "ridgeland, mississippi": "United States",
    "rio grande do sul, brasil": "Brazil",
    "roc": "United States",
    "rochdale, england": "United Kingdom",
    "rochester mills, pa": "United States",
    "rochester, ny": "United States",
    "rockchester": "United States",
    "rockland, ontario": "Canada",
    "rockstar land": "United States",
    "rolling with gangs for $20": "Unknown",
    "rose creek, tn": "United States",
    "roslindale": "United States",
    "rosscarbery, co. cork": "Ireland",
    "rotherham/england/uk": "United Kingdom",
    "row b seat 104": "United States",
    "roxboro, nc": "United States",
    "rva": "United States",
    "ryan medeiros": "Brazil",
    "s. wales": "United Kingdom",
    "sabah": "Malaysia",
    "sacramento, ca": "United States",
    "sailing the caribbean": "United States",
    "saint louis mo.": "United States",
    "saint louis, mo": "United States",
    "salford, greater manchester": "United Kingdom",
    "salinas california": "United States",
    "salinas los angeles, ca": "United States",
    "salinas, ca": "United States",
    "salt lake city, ut": "United States",
    "salt lake city, utah": "United States",
    "san antonio": "United States",
    "san antonio, tx": "United States",
    "san antonio,tx": "United States",
    "san buenaventura ventura ca": "United States",
    "san diego": "United States",
    "san diego county": "United States",
    "san diego, ca": "United States",
    "san francisco": "United States",
    "san francisco bay area": "United States",
    "san francisco bay area, usa": "United States",
    "san francisco, ca": "United States",
    "san francisco, ca, usa": "United States",
    "san isidro - argentina": "Argentina",
    "san jose, ca": "United States",
    "sango otta, nigeria": "Nigeria",
    "santa barbara, ca": "United States",
    "santa brbara, tf +34 67873941": "Spain",
    "santa cruz de tenerife espaa": "Spain",
    "santa cruz de tenerife espana": "Spain",
    "santa cruz, ca": "United States",
    "santa fe, nm": "United States",
    "santa monica, ca. usa, earth": "United States",
    "santo domingo": "Dominican Republic",
    "saraland": "United States",
    "sarasota, fl": "United States",
    "saskatoon": "Canada",
    "satan's armpit, usa": "Unknown",
    "saw ari 21/5/15": "Egypt",
    "scarborough, england": "United Kingdom",
    "scotland": "United Kingdom",
    "scotland, uk": "United Kingdom",
    "scotland, united kingdom": "United Kingdom",
    "scottish borders": "United Kingdom",
    "scottsdale, az": "United States",
    "scranton, pa": "United States",
    "search & destroy": "United States",
    "seatpleasant , md": "United States",
    "seattle": "United States",
    "seattle, united states": "United States",
    "seattle, wa": "United States",
    "seattle/bellevue,washington": "United States",
    "sec country": "Czechia",
    "sel loml": "India",
    "selma, ca": "United States",
    "send pictures of the sky": "Switzerland",
    "serris": "France",
    "sevensickos": "United States",
    "sf": "United States",
    "sf bay area, ca": "United States",
    "shakespeare country": "United Kingdom",
    "she/her": "Bosnia & Herzegovina",
    "she/her  yugihoes": "Unknown",
    "sheboygan wi": "United States",
    "sheffield": "United Kingdom",
    "sheffield uk": "United Kingdom",
    "sheffield, england": "United Kingdom",
    "sheho canada": "Canada",
    "shelby twp, mi": "United States",
    "shibuya, japan": "Japan",
    "shoeburyness": "United Kingdom",
    "shreveport, la": "United States",
    "shrewsbury": "United States",
    "shs/camano island": "United States",
    "sialkot, pakistan": "Pakistan",
    "sicily-italy": "Italy",
    "singapore": "Singapore",
    "skipton, north yorkshire": "United Kingdom",
    "sl '16": "United States",
    "slovakia": "Slovakia",
    "small town, usa": "United States",
    "so paulo, brazil": "Brazil",
    "socal": "United States",
    "soflo": "United States",
    "somerset": "United States",
    "somewhere": "United States",
    "somewhere in paris.": "France",
    "somewhere in west africa. #mufc": "Unknown",
    "somewhere mobbin __b": "Unknown",
    "somewhere over the rainbow": "United States",
    "somewhere small in pa": "Unknown",
    "somewhere stealing wifi, ny": "Unknown",
    "sophia": "United States",
    "soundview, bronx": "United States",
    "south africa": "South Africa",
    "south coast": "United States",
    "south east, england": "United Kingdom",
    "south jordan, ut": "United States",
    "south portland, me": "United States",
    "south puget sound": "United States",
    "south suburbs of chicago, il": "United States",
    "south uk": "United Kingdom",
    "south west, england": "United Kingdom",
    "southampton": "United Kingdom",
    "southeast texas": "United States",
    "southend-on-sea": "United Kingdom",
    "southern california": "United States",
    "southern indiana": "United States",
    "southern utah": "United States",
    "southside, houston, tx": "United States",
    "soweto": "South Africa",
    "space": "United States",
    "sper-fish sd": "United States",
    "spokane, washington": "United States",
    "spooky five-0 hq": "India",
    "spooptown": "United States",
    "springdale, arkansas": "United States",
    "springfield tn": "United States",
    "springfield, illinois": "United States",
    "springfield, ma": "United States",
    "springs": "South Africa",
    "st louis mo": "United States",
    "st. albans, vermont": "United States",
    "st. john's, newfoundland": "Canada",
    "st. john's, nl, canada": "Canada",
    "st. louis": "United States",
    "st. louis, missouri": "United States",
    "st. louis, mo": "United States",
    "st. petersburg, fla.": "United States",
    "st. petersburg, florida": "United States",
    "stadium of light": "United Kingdom",
    "staffordshire, uk": "United Kingdom",
    "stansted mountfitchet": "United Kingdom",
    "staten island, ny": "United States",
    "statesville, nc": "United States",
    "steamboat springs, colorado": "United States",
    "steroline sandwich": "Unknown",
    "stillwater, ok": "United States",
    "stockholm": "Sweden",
    "stockton-on-tees, england": "United Kingdom",
    "storrs, connecticut": "United States",
    "strawberry fields": "United States",
    "studio e": "United States",
    "stuttgart - germany": "Germany",
    "subconscious la": "United States",
    "sunny california": "United States",
    "sunny florida": "United States",
    "sunny southwest england": "United Kingdom",
    "surabaya": "Indonesia",
    "surf city, usa": "United States",
    "surprise, az": "United States",
    "surrey": "United Kingdom",
    "surrey, uk": "United Kingdom",
    "sussex": "United States",
    "sussex,london,kent & hampshire": "United Kingdom",
    "sutherland scotland": "United Kingdom",
    "sutton in ashfield, england": "United Kingdom",
    "sw florida": "United States",
    "sw scotland 100% scots": "United Kingdom",
    "swanscombe, england": "United Kingdom",
    "sweden": "Sweden",
    "sweet home alabama!": "United States",
    "sweet home, or": "United States",
    "switzerland": "Switzerland",
    "sword & cross": "United States",
    "sydney": "Australia",
    "sydney australia": "Australia",
    "sydney, australia": "Australia",
    "syria": "Syria",
    "t.o 416": "United States",
    "t: 34.021188,-118.375774": "United States",
    "t: 40.288708,-74.292437": "United States",
    "t: 41.493113,-81.703067": "United States",
    "t: 52.673237,-1.835459": "United States",
    "t: 53.5103067,-2.5253403": "United States",
    "t_bingen, germany": "Germany",
    "tabanan-bali": "Indonesia",
    "tacoma wa": "United States",
    "tacoma, washington": "United States",
    "taguig city": "Philippines",
    "tallahassee, fl": "United States",
    "tampa": "United States",
    "tampa bay, florida": "United States",
    "tampa fl": "United States",
    "tampa, fl": "United States",
    "tamworth, staffordshire": "United Kingdom",
    "taos new mexico": "United States",
    "tashkent, uzbekistan": "Uzbekistan",
    "taunton": "United States",
    "tauranga, new zealand": "New Zealand",
    "teen wolf": "United States",
    "teesside": "United Kingdom",
    "tejas": "United States",
    "tel aviv, israel": "Israel",
    "tembisa guateng": "South Africa",
    "texarkana_arlington, tx": "United States",
    "texas": "United States",
    "texas a&m university '18": "United States",
    "texas forever": "United States",
    "texas, usa": "United States",
    "thailand malaysia indonesia": "Malaysia",
    "the 402": "United States",
    "the alexandria safe zone.": "United States",
    "the bar": "United States",
    "the bay area": "United States",
    "the bay to a": "United States",
    "the brownstone": "United States",
    "the bus": "United States",
    "the citadel": "United States",
    "the city": "United States",
    "the dirty bitch": "Unknown",
    "the fruit bowl": "United States",
    "the gaza empire": "United States",
    "the gym": "United States",
    "the hague": "Netherlands",
    "the haven": "United States",
    "the hills of hp.": "United States",
    "the hoosier state": "United States",
    "the infinite universe": "United States",
    "the island.": "Iceland",
    "the long way home": "United States",
    "the middle of the bloody woods": "United States",
    "the moon": "United States",
    "the muthalovin 806": "United States",
    "the national assembly, cardiff": "United Kingdom",
    "the netherlands": "Netherlands",
    "the nightosphere, ireland": "Unknown",
    "the shire of york": "Australia",
    "the south": "United States",
    "the stars": "United States",
    "the sunshine state": "United States",
    "the swamp": "United States",
    "the universe": "United States",
    "the village": "United States",
    "thehoneymoontour/uk": "India",
    "they/she": "India",
    "they/them": "India",
    "this is us": "United States",
    "thizzlaam": "Unknown",
    "tigre, argentina.": "Argentina",
    "tlokweng, botswana": "Botswana",
    "tn": "United States",
    "tokyo": "Japan",
    "tokyo, japan": "Japan",
    "tomkins cove, ny": "United States",
    "tommorowland": "United States",
    "top floor office": "United States",
    "torbay, england": "United Kingdom",
    "toronto": "Canada",
    "toronto ontario": "Canada",
    "toronto, & london, england": "United Kingdom",
    "toronto, canada": "Canada",
    "toronto, on": "Canada",
    "toronto, on  canada": "Canada",
    "toronto, on.": "Canada",
    "toronto, ontario": "Canada",
    "toronto, ontario, canada": "Canada",
    "toronto, ontario_": "Canada",
    "torres novas": "Portugal",
    "towson, md": "United States",
    "trafford": "United Kingdom",
    "trash bin": "United States",
    "tree hill": "United States",
    "trenton": "United States",
    "trinidad & tobago": "Trinidad and Tobago",
    "trj. __": "India",
    "trondheim, norway": "Norway",
    "troy, mi": "United States",
    "ts & lm defense squad": "Unknown",
    "ts,ed,1d": "Germany",
    "tucson, arizona": "United States",
    "tucson, az": "United States",
    "tulalip, washington": "United States",
    "tulsa/stillwater": "United States",
    "tunisie": "Tunisia",
    "turkey": "Turkey",
    "tuscaloosa, al": "United States",
    "twitter": "United States",
    "twittersphere": "Unknown",
    "tx": "United States",
    "tx / ny": "United States",
    "tyler, tx": "United States",
    "u.k": "United Kingdom",
    "ua": "United States",
    "uae - dubai": "United Arab Emirates",
    "udaipur": "India",
    "uk": "United Kingdom",
    "uk-us": "United States",
    "uma": "United States",
    "under a tree": "United States",
    "uni of nv": "United States",
    "unilag": "Nigeria",
    "united arab emirates": "United Arab Emirates",
    "united kingdom": "United Kingdom",
    "united kingdom - saudi arabia": "United Kingdom",
    "united states": "United States",
    "united states of america": "United States",
    "university": "United States",
    "university of calgary": "Canada",
    "university of huddersfield, uk": "United Kingdom",
    "university of surrey": "United Kingdom",
    "unknown": "United States",
    "upt..where the loud things are": "Unknown",
    "us": "United States",
    "us east coast": "United States",
    "us, europe, australia & asia": "Netherlands",
    "usa": "United States",
    "usa, ashland": "United States",
    "usa, global": "United States",
    "usa, maine": "United States",
    "usf": "United States",
    "usm": "United States",
    "utah": "United States",
    "valdosta, ga": "United States",
    "valencia (spain)": "Spain",
    "vancouver": "Canada",
    "vancouver, bc": "Canada",
    "vancouver, british columbia": "Canada",
    "vancouver, canada": "Canada",
    "vasc": "United States",
    "vegas": "United States",
    "vegas by way of chicago": "United States",
    "venezuela": "Venezuela",
    "venice": "Italy",
    "venice, ca": "United States",
    "venice, fl": "United States",
    "venus  ny  fl": "United States",
    "vermont": "United States",
    "vermont, burlington": "United States",
    "verona": "Italy",
    "victoria, bc": "Canada",
    "victoria, bc, canada": "Canada",
    "vienna": "Austria",
    "villa di tirano, italia": "Italy",
    "village of clarkston, mi": "United States",
    "virginia": "United States",
    "virginia beach": "United States",
    "virginia, usa": "United States",
    "volusia & flagler counties": "United States",
    "w.london / the food cupboard": "United States",
    "w/ courtland_": "United States",
    "waco tx": "United States",
    "waco, tx": "United States",
    "wake forest, nc": "United States",
    "wales": "United Kingdom",
    "wales, united kingdom": "United Kingdom",
    "wall street, ny": "United States",
    "wandsworth, london": "United Kingdom",
    "was in the u.s. durban now!": "Unknown",
    "washington d.c.": "United States",
    "washington dc": "United States",
    "washington dc area": "United States",
    "washington dc metro area": "United States",
    "washington state": "United States",
    "washington state usa": "United States",
    "washington, d.c.": "United States",
    "washington, dc": "United States",
    "washington, dc area": "United States",
    "washington, usa": "United States",
    "wasilla, ak": "United States",
    "waterford, ireland": "Ireland",
    "watford uk": "United Kingdom",
    "watford, hertfordshire": "United Kingdom",
    "wayne, michigan": "United States",
    "web": "United States",
    "welland, ontario": "Canada",
    "wellington, new zealand": "New Zealand",
    "wellington, nz": "New Zealand",
    "welshpool": "United Kingdom",
    "wereldburger": "Netherlands",
    "wesley.lowery@washpost.com": "Unknown",
    "wessex": "United States",
    "west chester university": "United States",
    "west cornwall": "United States",
    "west lafayette, ind.": "United States",
    "west midlands, england": "United Kingdom",
    "west midlands, uk": "United Kingdom",
    "west mids": "United Kingdom",
    "west palm beach, fl usa": "United States",
    "west virgina": "United States",
    "west virginia/new york": "United States",
    "west yorkshire, uk": "United Kingdom",
    "west$ide": "United States",
    "western & central pa": "United States",
    "western cape": "South Africa",
    "western u, ontario": "Canada",
    "westeros": "India",
    "westfield, in": "United States",
    "weybridge, surrey.": "United Kingdom",
    "weymouth": "United States",
    "what am i? hungry.": "United States",
    "where do you think?": "Unknown",
    "where dreams become reality": "Unknown",
    "where life & the dream collide": "United States",
    "where my heart is": "Canada",
    "where the grass stay green": "Pakistan",
    "where the wild things are": "United States",
    "wherever my queen demi is": "Unknown",
    "wherever the food is...": "United States",
    "white plains, md": "United States",
    "whitstable": "United Kingdom",
    "whittier, sunny so cal": "United States",
    "wichita falls, texas": "United States",
    "wichita, ks": "United States",
    "wildcat city": "United States",
    "willard, oh": "United States",
    "william pitt union, pittsburgh": "United States",
    "wilmington, de": "United States",
    "wilmington, nc": "United States",
    "wilmington, ohio": "United States",
    "winchester": "United States",
    "winchester, uk": "United Kingdom",
    "windhoek , namibia": "Namibia",
    "windsor park,new zealand": "New Zealand",
    "winelands, cape town": "South Africa",
    "winfield, kansas": "United States",
    "winona lake, ind.": "United States",
    "winston salem, nc": "United States",
    "winter park, florida": "United States",
    "wirral, england": "United Kingdom",
    "wisconsin": "United States",
    "wisconsin, usa": "United States",
    "wishaniggawoods": "Unknown",
    "with sam on zebes": "Unknown",
    "witney, oxfordshire": "United Kingdom",
    "witt shae": "United States",
    "wku_": "United States",
    "wolfpac city, michigan, usa": "United States",
    "wolverhampton": "United Kingdom",
    "wonderland": "Canada",
    "worcester": "United States",
    "worcester, ma": "United States",
    "worcestershire": "United Kingdom",
    "worcestershire, uk": "United Kingdom",
    "work": "Singapore",
    "world": "United States",
    "world of minecraft, new york": "Unknown",
    "world wide web": "United States",
    "world without end": "United States",
    "worldwide": "United States",
    "worthing, england": "United Kingdom",
    "worthing, uk": "United Kingdom",
    "wr5": "United Kingdom",
    "wright anything agency": "United States",
    "www.youtube.com/undistone": "Unknown",
    "wylam, northumberland.": "United Kingdom",
    "wylie, tx": "United States",
    "wynona": "United States",
    "xviii.i.xv": "Brazil",
    "yapton, england": "United Kingdom",
    "yay area": "United States",
    "yay area; bay area": "United States",
    "yeniehir, mersin": "Turkey",
    "yorkshire": "United States",
    "yorkville, il": "United States",
    "you're not 19 forever": "Unknown",
    "youtube": "United States",
    "yverdon": "Switzerland",
    "zadar, croatia": "Croatia",
    "zinzinnati": "United States",
    "|| spncw || samandriels ||": "Unknown",
    "|| taken || nini|| 010115": "Unknown",
    "~halloween town~": "United States"
}